spliceaitoolkit/__init__.py
spliceaitoolkit/constants.py
spliceaitoolkit/header.py
spliceaitoolkit/spliceaitoolkit.py
spliceaitoolkit/create_data/__init__.py
spliceaitoolkit/create_data/create_datafile.py
spliceaitoolkit/create_data/create_dataset.py
spliceaitoolkit/create_data/utils.py
spliceaitoolkit/create_data/verify_h5_file.py
spliceaitoolkit/create_dataset/Step_1_create_datafile.py
spliceaitoolkit/create_dataset/Step_2_create_dataset.py
spliceaitoolkit/create_dataset/Step_2_create_dataset_noh5py.py
spliceaitoolkit/create_dataset/Step_3_verify_h5_file.py
spliceaitoolkit/create_dataset/__init__.py
spliceaitoolkit/create_dataset/constants.py
spliceaitoolkit/fine_tune/__init__.py
spliceaitoolkit/fine_tune/fine_tune.py
spliceaitoolkit/fine_tune/spliceai.py
spliceaitoolkit/fine_tune/utils.py
spliceaitoolkit/predict/__init__.py
spliceaitoolkit/predict/predict.py
spliceaitoolkit/scripts_create_dataset/Step_1_create_datafile.py
spliceaitoolkit/scripts_create_dataset/Step_2_create_dataset.py
spliceaitoolkit/scripts_create_dataset/Step_2_create_dataset_noh5py.py
spliceaitoolkit/scripts_create_dataset/Step_3_verify_h5_file.py
spliceaitoolkit/scripts_create_dataset/__init__.py
spliceaitoolkit/scripts_create_dataset/constants.py
spliceaitoolkit/train/__init__.py
spliceaitoolkit/train/spliceai copy.py
spliceaitoolkit/train/spliceai.py
spliceaitoolkit/train/train.py
spliceaitoolkit/train/utils.py
spliceaitoolkit/variant/__init__.py
spliceaitoolkit/variant/utils.py
spliceaitoolkit/variant/variant.py
spliceai_toolkit-0.0.1.dist-info/LICENSE
spliceai_toolkit-0.0.1.dist-info/METADATA
spliceai_toolkit-0.0.1.dist-info/WHEEL
spliceai_toolkit-0.0.1.dist-info/entry_points.txt
spliceai_toolkit-0.0.1.dist-info/top_level.txt
spliceai_toolkit-0.0.1.dist-info/RECORD
