Metadata-Version: 2.1
Name: spliceai-toolkit
Version: 0.0.1
Summary: A splice site preditction toolkit
Home-page: https://github.com/Kuanhao-Chao/spliceAI-toolkit
Author: Kuan-Hao Chao
Author-email: kh.chao@cs.jhu.edu
Requires-Python: >=3.6
License-File: LICENSE
